{ "compressionlevel":-1,
 "height":6,
 "infinite":false,
 "layers":[
        {
         "data":[38, 46, 45, 46, 38,
            38, 46, 45, 46, 38,
            38, 46, 45, 46, 38,
            38, 46, 45, 46, 38,
            38, 46, 45, 46, 38,
            38, 46, 45, 46, 38],
         "height":6,
         "id":8,
         "name":"tiles",
         "opacity":1,
         "type":"tilelayer",
         "visible":true,
         "width":5,
         "x":0,
         "y":0
        }, 
        {
         "data":[49, 2147483696, 49, 2147483696, 49,
            0, 0, 0, 0, 0,
            18, 0, 0, 0, 18,
            22, 0, 0, 0, 22,
            0, 0, 0, 0, 0,
            1073741873, 1073741872, 1073741873, 1073741872, 1073741873],
         "height":6,
         "id":9,
         "name":"object1",
         "opacity":1,
         "type":"tilelayer",
         "visible":true,
         "width":5,
         "x":0,
         "y":0
        }],
 "nextlayerid":10,
 "nextobjectid":1,
 "orientation":"orthogonal",
 "renderorder":"right-down",
 "tiledversion":"1.10.2",
 "tileheight":90,
 "tilesets":[
        {
         "columns":1,
         "firstgid":1,
         "image":"..\/public\/towers\/tower_2.png",
         "imageheight":90,
         "imagewidth":64,
         "margin":0,
         "name":"tower1",
         "spacing":0,
         "tilecount":1,
         "tileheight":90,
         "tilewidth":64
        }, 
        {
         "columns":5,
         "firstgid":2,
         "image":"..\/public\/tiles\/hex_tilesheet.png",
         "imageheight":540,
         "imagewidth":320,
         "margin":0,
         "name":"hex_sheet",
         "spacing":0,
         "tilecount":30,
         "tileheight":90,
         "tilewidth":64
        }, 
        {
         "columns":4,
         "firstgid":32,
         "image":"..\/public\/tiles\/tiles_1.png",
         "imageheight":360,
         "imagewidth":256,
         "margin":0,
         "name":"tiles_1",
         "spacing":0,
         "tilecount":16,
         "tileheight":90,
         "tilewidth":64
        }, 
        {
         "columns":1,
         "firstgid":48,
         "image":"..\/public\/items\/brown_tree.png",
         "imageheight":90,
         "imagewidth":64,
         "margin":0,
         "name":"brown_tree",
         "spacing":0,
         "tilecount":1,
         "tileheight":90,
         "tilewidth":64
        }, 
        {
         "columns":1,
         "firstgid":49,
         "image":"..\/public\/towers\/brick_house_2.png",
         "imageheight":64,
         "imagewidth":64,
         "margin":0,
         "name":"brick_house_2",
         "spacing":0,
         "tilecount":1,
         "tileheight":64,
         "tilewidth":64
        }],
 "tilewidth":64,
 "type":"map",
 "version":"1.10",
 "width":5
}